deltasimulator/__about__.py
deltasimulator/__init__.py
deltasimulator/lib.py
deltasimulator/build_tools/__init__.py
deltasimulator/build_tools/cogify.py
deltasimulator/build_tools/environment.py
deltasimulator/build_tools/fileio.py
deltasimulator/build_tools/utils.py
deltasimulator/build_tools/environments/__init__.py
deltasimulator/build_tools/environments/cppenv.py
deltasimulator/build_tools/environments/host.py
deltasimulator/build_tools/environments/pythonator.py
deltasimulator/build_tools/environments/verilator.py
deltasimulator/build_tools/environments/wiringenv.py
deltasimulator-0.6.1.dist-info/LICENSE.rst
deltasimulator-0.6.1.dist-info/METADATA
deltasimulator-0.6.1.dist-info/WHEEL
deltasimulator-0.6.1.dist-info/top_level.txt
deltasimulator-0.6.1.dist-info/RECORD
