Metadata-Version: 2.1
Name: deltasimulator
Version: 0.6.1
Summary: Runs Deltaflow programs on virtual platforms
Home-page: https://github.com/riverlane/deltasimulator
Author: Riverlane
Author-email: deltaflow@riverlane.com
License: MIT License with Commons Clause
Platform: Ubuntu 20.04
Classifier: Development Status :: 5 - Production/Stable
Classifier: Environment :: Console
Classifier: Intended Audience :: Developers
Classifier: Intended Audience :: Science/Research
Classifier: License :: Free for non-commercial use
Classifier: Operating System :: POSIX :: Linux
Classifier: Programming Language :: C++
Classifier: Programming Language :: Python :: 3
Classifier: Topic :: Software Development :: Embedded Systems
Classifier: Topic :: System :: Emulators
Requires-Python: ==3.8.*
Requires-Dist: cogapp (>=3.0)
Requires-Dist: deltalanguage (==0.6.3)
Requires-Dist: dill (>=0.3)
Requires-Dist: find-libpython (>=0.1)
